setup.py
collate_patient_logfiles/__init__.py
collate_patient_logfiles/collate_patient_logfiles.py
collate_patient_logfiles.egg-info/PKG-INFO
collate_patient_logfiles.egg-info/SOURCES.txt
collate_patient_logfiles.egg-info/dependency_links.txt
collate_patient_logfiles.egg-info/entry_points.txt
collate_patient_logfiles.egg-info/requires.txt
collate_patient_logfiles.egg-info/top_level.txt