Metadata-Version: 1.0
Name: collate-patient-logfiles
Version: 0.2.0
Summary: Collate logfile data.
Home-page: UNKNOWN
Author: Simon Biggs
Author-email: mail@simonbiggs.net
License: AGPL3+
Platform: UNKNOWN
